polars_io/__init__.py
polars_io/common.py
polars_io/fixed_width.py
polars_io/lines.py
polars_io/sas.py
polars_io/stata.py
polars_io-0.5.0.dist-info/METADATA
polars_io-0.5.0.dist-info/WHEEL
polars_io-0.5.0.dist-info/RECORD
