Metadata-Version: 2.4
Name: polars-io
Version: 0.5.0
Summary: Lazy and eager reading of Stata and SAS files into Polars
Author-email: Alistair Pattison <alistairpattison@gmail.com>
Requires-Python: >=3.10
Requires-Dist: beartype>=0.21.0
Requires-Dist: polars>=1.31.0
Requires-Dist: pyarrow>=21.0.0
Requires-Dist: pyreadstat>=1.3.0
